pyopensky/__init__.py
pyopensky/api.py
pyopensky/config.py
pyopensky/py.typed
pyopensky/rest.py
pyopensky/s3.py
pyopensky/schema.py
pyopensky/time.py
pyopensky/trino.py
pyopensky/tzdata.py
pyopensky-2.15.dist-info/METADATA
pyopensky-2.15.dist-info/WHEEL
pyopensky-2.15.dist-info/RECORD
