Metadata-Version: 2.4
Name: pyopensky
Version: 2.15
Summary: A Python interface for OpenSky database
Project-URL: Repository, https://github.com/open-aviation/pyopensky/
Author-email: Xavier Olive <git@xoolive.org>, Junzi Sun <j.sun-1@tudelft.nl>
License-Expression: MIT
Requires-Python: >=3.9
Requires-Dist: appdirs>=1.4.4
Requires-Dist: httpx>=0.27.2
Requires-Dist: minio>=7.2.8
Requires-Dist: pandas>=2.2.2
Requires-Dist: pyarrow>=17.0.0
Requires-Dist: pyjwt>=2.9.0
Requires-Dist: python-dotenv>=1.0.1
Requires-Dist: tqdm>=4.66.5
Requires-Dist: trino[sqlalchemy]>=0.329.0
Requires-Dist: typing-extensions>=4.12.2
Requires-Dist: tzdata>=2024.2
Provides-Extra: cartes
Requires-Dist: cartes>=0.8.1; extra == 'cartes'
Provides-Extra: decoding
Requires-Dist: pymodes>=2.18; extra == 'decoding'
Requires-Dist: rs1090>=0.3.8; extra == 'decoding'
